Workbook

Sheet Cover

Sheet Fund Master Data
A1: MUTUAL FUND MASTER DATA — 20 FUND UNIVERSE
A2: Fund Name | B2: Category | C2: AMC / Fund House | D2: AUM (₹ Cr) | E2: Expense Ratio | F2: Beta | G2: Std Deviation % | H2: NAV — 5Y Ago (₹) | I2: NAV — 3Y Ago (₹) | J2: NAV — 1Y Ago (₹) | K2: NAV — Current (₹)
A3: Mirae Asset Large Cap Fund | B3: Equity | C3: Mirae Asset | D3: 37850 | E3: 0.0054 | F3: 0.97 | G3: 14.2 | H3: 42.15 | I3: 56.8 | J3: 71.35 | K3: 89.42
A4: Axis Bluechip Fund | B4: Equity | C4: Axis MF | D4: 34210 | E4: 0.0058 | F4: 0.92 | G4: 13.83 | H4: 46.25 | I4: 5.6 | J4: 13.83 | K4: 68.92
A5: HDFC Top 100 Fund | B5: Equity | C5: HDFC MF | D5: 29650 | E5: 0.0165 | F5: 1.05 | G5: 15.62 | H5: 38.9 | I5: 8.4 | J5: 15.62 | K5: 72.15
A6: Kotak Standard Multicap | B6: Equity | C6: Kotak MF | D6: 42310 | E6: 0.0058 | F6: 1.02 | G6: 14.93 | H6: 44.6 | I6: 1.8 | J6: 14.93 | K6: 78.3
A7: SBI Blue Chip Fund | B7: Equity | C7: SBI MF | D7: 31420 | E7: 0.0098 | F7: 0.95 | G7: 14.12 | H7: 40.2 | I7: 9.6 | J7: 14.12 | K7: 67.85
A8: Parag Parikh Flexi Cap | B8: Equity | C8: PPFAS MF | D8: 52140 | E8: 0.0063 | F8: 0.88 | G8: 13.52 | H8: 42.8 | I8: 6.4 | J8: 13.52 | K8: 84.2
A9: Nippon India Small Cap | B9: Equity | C9: Nippon MF | D9: 41230 | E9: 0.0074 | F9: 1.18 | G9: 19.81 | H9: 35.4 | I9: 8.6 | J9: 19.81 | K9: 112.4
A10: HDFC Mid-Cap Opportunities | B10: Equity | C10: HDFC MF | D10: 38920 | E10: 0.0165 | F10: 1.12 | G10: 18.23 | H10: 52.8 | I10: 2.5 | J10: 18.23 | K10: 128.6
A11: Aditya Birla PSU Equity | B11: Equity | C11: ABSL MF | D11: 4210 | E11: 0.0051 | F11: 1.22 | G11: 22.41 | H11: 18.6 | I11: 2.3 | J11: 22.41 | K11: 61.2
A12: DSP Midcap Fund | B12: Equity | C12: DSP MF | D12: 18640 | E12: 0.0085 | F12: 1.08 | G12: 17.52 | H12: 44.2 | I12: 8.4 | J12: 17.52 | K12: 102.8
A13: SBI Magnum Gilt Fund | B13: Debt | C13: SBI MF | D13: 8420 | E13: 0.0046 | F13: 0.18 | G13: 4.2 | H13: 40.2 | I13: 46.8 | J13: 51.6 | K13: 56.4
A14: HDFC Corporate Bond Fund | B14: Debt | C14: HDFC MF | D14: 28640 | E14: 0.0038 | F14: 0.22 | G14: 3.8 | H14: 18.6 | I14: 22.4 | J14: 25.8 | K14: 28.6
... A22: Canara Robeco Equity Hybrid | B22: Hybrid | C22: Canara Robeco | D22: 9840 | E22: 0.0066 | F22: 0.74 | G22: 11.5 | H22: 182.4 | I22: 228.6 | J22: 274.8 | K22: 322.4
A23: TOTALS / AVERAGES | D23: =SUM(D3:D22) -> 515300 | E23: =AVERAGE(E3:E22) -> 0.007165 | F23: =AVERAGE(F3:F22) -> 0.7405 | G23: =AVERAGE(G3:G22) -> 11.7395

Sheet Financial Calculations
A1: Risk-Free Rate (10Y G-Sec) | B1: 0.072
A2: Benchmark Annual Return | B2: 0.128
A4: Fund Name | B4: Category | C4: 1Y Return | D4: 3Y CAGR | E4: 5Y CAGR | F4: Sharpe Ratio | G4: Alpha | H4: Beta | I4: Std Dev % | J4: Expense % | K4: Overall Score
A5: ='Fund Master Data'!A3 -> Mirae Asset Large Cap Fund | B5: ='Fund Master Data'!B3 -> Equity | C5: =('Fund Master Data'!K3/'Fund Master Data'!J3)-1 -> 0.25325858 | D5: =('Fund Master Data'!K3/'Fund Master Data'!I3)^(1/3)-1 -> 0.16330995 | E5: =('Fund Master Data'!K3/'Fund Master Data'!H3)^(1/5)-1 -> 0.16232457 | F5: =(E5-$B$1)/('Fund Master Data'!G3/100) -> 0.6360885 | G5: =E5-($B$1+'Fund Master Data'!F3*($B$2-$B$1)) -> 0.036004567 | H5: ='Fund Master Data'!F3 -> 0.97 | I5: ='Fund Master Data'!G3 -> 14.2 | J5: ='Fund Master Data'!E3 -> 0.0054 | K5: =F5*40 + C5*100*30 + G5*100*30 -> 893.233
A6: ='Fund Master Data'!A4 -> Axis Bluechip Fund | B6: ='Fund Master Data'!B4 -> Equity | C6: =('Fund Master Data'!K4/'Fund Master Data'!J4)-1 -> 3.9833695 | D6: =('Fund Master Data'!K4/'Fund Master Data'!I4)^(1/3)-1 -> 1.308797 | E6: =('Fund Master Data'!K4/'Fund Master Data'!H4)^(1/5)-1 -> 0.08304551 | F6: =(E6-$B$1)/('Fund Master Data'!G4/100) -> 0.079866307 | G6: =E6-($B$1+'Fund Master Data'!F4*($B$2-$B$1)) -> -0.04047449 | H6: ='Fund Master Data'!F4 -> 0.92 | I6: ='Fund Master Data'!G4 -> 13.83 | J6: ='Fund Master Data'!E4 -> 0.0058 | K6: =F6*40 + C6*100*30 + G6*100*30 -> 11831.88
A7: ='Fund Master Data'!A5 -> HDFC Top 100 Fund | B7: ='Fund Master Data'!B5 -> Equity | C7: =('Fund Master Data'!K5/'Fund Master Data'!J5)-1 -> 3.6190781 | D7: =('Fund Master Data'!K5/'Fund Master Data'!I5)^(1/3)-1 -> 1.0479484 | E7: =('Fund Master Data'!K5/'Fund Master Data'!H5)^(1/5)-1 -> 0.13150727 | F7: =(E7-$B$1)/('Fund Master Data'!G5/100) -> 0.38096841 | G7: =E7-($B$1+'Fund Master Data'!F5*($B$2-$B$1)) -> 0.00070726519 | H7: ='Fund Master Data'!F5 -> 1.05 | I7: ='Fund Master Data'!G5 -> 15.62 | J7: ='Fund Master Data'!E5 -> 0.0165 | K7: =F7*40 + C7*100*30 + G7*100*30 -> 10874.595
A8: ='Fund Master Data'!A6 -> Kotak Standard Multicap | B8: ='Fund Master Data'!B6 -> Equity | C8: =('Fund Master Data'!K6/'Fund Master Data'!J6)-1 -> 4.2444742 | D8: =('Fund Master Data'!K6/'Fund Master Data'!I6)^(1/3)-1 -> 2.5169248 | E8: =('Fund Master Data'!K6/'Fund Master Data'!H6)^(1/5)-1 -> 0.11914248 | F8: =(E8-$B$1)/('Fund Master Data'!G6/100) -> 0.31575673 | G8: =E8-($B$1+'Fund Master Data'!F6*($B$2-$B$1)) -> -0.0099775204 | H8: ='Fund Master Data'!F6 -> 1.02 | I8: ='Fund Master Data'!G6 -> 14.93 | J8: ='Fund Master Data'!E6 -> 0.0058 | K8: =F8*40 + C8*100*30 + G8*100*30 -> 12716.12
A9: ='Fund Master Data'!A7 -> SBI Blue Chip Fund | B9: ='Fund Master Data'!B7 -> Equity | C9: =('Fund Master Data'!K7/'Fund Master Data'!J7)-1 -> 3.8052408 | D9: =('Fund Master Data'!K7/'Fund Master Data'!I7)^(1/3)-1 -> 0.91907909 | E9: =('Fund Master Data'!K7/'Fund Master Data'!H7)^(1/5)-1 -> 0.11036243 | F9: =(E9-$B$1)/('Fund Master Data'!G7/100) -> 0.27168862 | G9: =E9-($B$1+'Fund Master Data'!F7*($B$2-$B$1)) -> -0.014837567 | H9: ='Fund Master Data'!F7 -> 0.95 | I9: ='Fund Master Data'!G7 -> 14.12 | J9: ='Fund Master Data'!E7 -> 0.0098 | K9: =F9*40 + C9*100*30 + G9*100*30 -> 11382.077
A10: ='Fund Master Data'!A8 -> Parag Parikh Flexi Cap | B10: ='Fund Master Data'!B8 -> Equity | C10: =('Fund Master Data'!K8/'Fund Master Data'!J8)-1 -> 5.2278107 | D10: =('Fund Master Data'!K8/'Fund Master Data'!I8)^(1/3)-1 -> 1.3607176 | E10: =('Fund Master Data'!K8/'Fund Master Data'!H8)^(1/5)-1 -> 0.14491611 | F10: =(E10-$B$1)/('Fund Master Data'!G8/100) -> 0.5393203 | G10: =E10-($B$1+'Fund Master Data'!F8*($B$2-$B$1)) -> 0.023636105 | H10: ='Fund Master Data'!F8 -> 0.88 | I10: ='Fund Master Data'!G8 -> 13.52 | J10: ='Fund Master Data'!E8 -> 0.0063 | K10: =F10*40 + C10*100*30 + G10*100*30 -> 15775.913
A11: ='Fund Master Data'!A9 -> Nippon India Small Cap | B11: ='Fund Master Data'!B9 -> Equity | C11: =('Fund Master Data'!K9/'Fund Master Data'!J9)-1 -> 4.6739021 | D11: =('Fund Master Data'!K9/'Fund Master Data'!I9)^(1/3)-1 -> 1.3555335 | E11: =('Fund Master Data'!K9/'Fund Master Data'!H9)^(1/5)-1 -> 0.25994797 | F11: =(E11-$B$1)/('Fund Master Data'!G9/100) -> 0.94875298 | G11: =E11-($B$1+'Fund Master Data'!F9*($B$2-$B$1)) -> 0.12186797 | H11: ='Fund Master Data'!F9 -> 1.18 | I11: ='Fund Master Data'!G9 -> 19.81 | J11: ='Fund Master Data'!E9 -> 0.0074 | K11: =F11*40 + C11*100*30 + G11*100*30 -> 14425.26
A12: ='Fund Master Data'!A10 -> HDFC Mid-Cap Opportunities | B12: ='Fund Master Data'!B10 -> Equity | C12: =('Fund Master Data'!K10/'Fund Master Data'!J10)-1 -> 6.0543061 | D12: =('Fund Master Data'!K10/'Fund Master Data'!I10)^(1/3)-1 -> 2.719064 | E12: =('Fund Master Data'!K10/'Fund Master Data'!H10)^(1/5)-1 -> 0.19487207 | F12: =(E12-$B$1)/('Fund Master Data'!G10/100) -> 0.67401025 | G12: =E12-($B$1+'Fund Master Data'!F10*($B$2-$B$1)) -> 0.060152069 | H12: ='Fund Master Data'!F10 -> 1.12 | I12: ='Fund Master Data'!G10 -> 18.23 | J12: ='Fund Master Data'!E10 -> 0.0165 | K12: =F12*40 + C12*100*30 + G12*100*30 -> 18370.335
A13: ='Fund Master Data'!A11 -> Aditya Birla PSU Equity | B13: ='Fund Master Data'!B11 -> Equity | C13: =('Fund Master Data'!K11/'Fund Master Data'!J11)-1 -> 1.7309237 | D13: =('Fund Master Data'!K11/'Fund Master Data'!I11)^(1/3)-1 -> 1.9854367 | E13: =('Fund Master Data'!K11/'Fund Master Data'!H11)^(1/5)-1 -> 0.26895931 | F13: =(E13-$B$1)/('Fund Master Data'!G11/100) -> 0.87889026 | G13: =E13-($B$1+'Fund Master Data'!F11*($B$2-$B$1)) -> 0.12863931 | H13: ='Fund Master Data'!F11 -> 1.22 | I13: ='Fund Master Data'!G11 -> 22.41 | J13: ='Fund Master Data'!E11 -> 0.0051 | K13: =F13*40 + C13*100*30 + G13*100*30 -> 5613.8446
A14: ='Fund Master Data'!A12 -> DSP Midcap Fund | B14: ='Fund Master Data'!B12 -> Equity | C14: =('Fund Master Data'!K12/'Fund Master Data'!J12)-1 -> 4.8675799 | D14: =('Fund Master Data'!K12/'Fund Master Data'!I12)^(1/3)-1 -> 1.3044712 | E14: =('Fund Master Data'!K12/'Fund Master Data'!H12)^(1/5)-1 -> 0.18389768 | F14: =(E14-$B$1)/('Fund Master Data'!G12/100) -> 0.63868538 | G14: =E14-($B$1+'Fund Master Data'!F12*($B$2-$B$1)) -> 0.051417679 | H14: ='Fund Master Data'!F12 -> 1.08 | I14: ='Fund Master Data'!G12 -> 17.52 | J14: ='Fund Master Data'!E12 -> 0.0085 | K14: =F14*40 + C14*100*30 + G14*100*30 -> 14782.54
A15: ='Fund Master Data'!A13 -> SBI Magnum Gilt Fund | B15: ='Fund Master Data'!B13 -> Debt | C15: =('Fund Master Data'!K13/'Fund Master Data'!J13)-1 -> 0.093023256 | D15: =('Fund Master Data'!K13/'Fund Master Data'!I13)^(1/3)-1 -> 0.064170177 | E15: =('Fund Master Data'!K13/'Fund Master Data'!H13)^(1/5)-1 -> 0.070066111 | F15: =(E15-$B$1)/('Fund Master Data'!G13/100) -> -0.046044975 | G15: =E15-($B$1+'Fund Master Data'!F13*($B$2-$B$1)) -> -0.012013889 | H15: ='Fund Master Data'!F13 -> 0.18 | I15: ='Fund Master Data'!G13 -> 4.2 | J15: ='Fund Master Data'!E13 -> 0.0046 | K15: =F15*40 + C15*100*30 + G15*100*30 -> 241.1863
A16: ='Fund Master Data'!A14 -> HDFC Corporate Bond Fund | B16: ='Fund Master Data'!B14 -> Debt | C16: =('Fund Master Data'!K14/'Fund Master Data'!J14)-1 -> 0.10852713 | D16: =('Fund Master Data'!K14/'Fund Master Data'!I14)^(1/3)-1 -> 0.08485744 | E16: =('Fund Master Data'!K14/'Fund Master Data'!H14)^(1/5)-1 -> 0.08985976 | F16: =(E16-$B$1)/('Fund Master Data'!G14/100) -> 0.46999368 | G16: =E16-($B$1+'Fund Master Data'!F14*($B$2-$B$1)) -> 0.00553976 | H16: ='Fund Master Data'!F14 -> 0.22 | I16: ='Fund Master Data'!G14 -> 3.8 | J16: ='Fund Master Data'!E14 -> 0.0038 | K16: =F16*40 + C16*100*30 + G16*100*30 -> 361.00042
... A24: ='Fund Master Data'!A22 -> Canara Robeco Equity Hybrid | B24: ='Fund Master Data'!B22 -> Hybrid | C24: =('Fund Master Data'!K22/'Fund Master Data'!J22)-1 -> 0.17321689 | D24: =('Fund Master Data'!K22/'Fund Master Data'!I22)^(1/3)-1 -> 0.12143198 | E24: =('Fund Master Data'!K22/'Fund Master Data'!H22)^(1/5)-1 -> 0.12066044 | F24: =(E24-$B$1)/('Fund Master Data'!G22/100) -> 0.42313423 | G24: =E24-($B$1+'Fund Master Data'!F22*($B$2-$B$1)) -> 0.0072204361 | H24: ='Fund Master Data'!F22 -> 0.74 | I24: ='Fund Master Data'!G22 -> 11.5 | J24: ='Fund Master Data'!E22 -> 0.0066 | K24: =F24*40 + C24*100*30 + G24*100*30 -> 558.23733
A25: UNIVERSE AVERAGES | C25: =AVERAGE(C5:C24) -> 1.9983539 | D25: =AVERAGE(D5:D24) -> 0.78672588 | E25: =AVERAGE(E5:E24) -> 0.13567042 | F25: =AVERAGE(F5:F24) -> 0.44067235 | G25: =AVERAGE(G5:G24) -> 0.02220242 | I25: =AVERAGE(I5:I24) -> 11.7395 | J25: =AVERAGE(J5:J24) -> 0.007165

Sheet Risk-Return Analysis
A3: Fund Name | B3: Category | C3: 5Y CAGR | D3: Sharpe | E3: Alpha | F3: Beta | G3: Std Dev% | H3: Quadrant | I3: Rank (5Y)
A4: ='Financial Calculations'!A5 -> Mirae Asset Large Cap Fund | B4: ='Financial Calculations'!B5 -> Equity | C4: ='Financial Calculations'!E5 -> 0.16232457 | D4: ='Financial Calculations'!F5 -> 0.6360885 | E4: ='Financial Calculations'!G5 -> 0.036004567 | F4: ='Financial Calculations'!H5 -> 0.97 | G4: ='Financial Calculations'!I5 -> 14.2 | H4: =IF(AND(C4>='Financial Calculations'!$C$25,G4<'Financial Calculations'!$I$25), "⭐ STAR", IF(AND(C4>='Financial Calculations'!$C$25,G4>='Financial Calculations'!$I$25), "🔥 AGGRESSIVE", IF(AND(C4<'Financial Calculations'!$C$25,G4<'Financial Calculations'!$I$25), "💙 STEADY", "⚠️ AVOID"))) -> ⚠️ AVOID | I4: =RANK(C4,$C$4:$C$23,0) -> 5
A5: ='Financial Calculations'!A6 -> Axis Bluechip Fund | B5: ='Financial Calculations'!B6 -> Equity | C5: ='Financial Calculations'!E6 -> 0.08304551 | D5: ='Financial Calculations'!F6 -> 0.079866307 | E5: ='Financial Calculations'!G6 -> -0.04047449 | F5: ='Financial Calculations'!H6 -> 0.92 | G5: ='Financial Calculations'!I6 -> 13.83 | H5: =IF(AND(C5>='Financial Calculations'!$C$25,G5<'Financial Calculations'!$I$25), "⭐ STAR", IF(AND(C5>='Financial Calculations'!$C$25,G5>='Financial Calculations'!$I$25), "🔥 AGGRESSIVE", IF(AND(C5<'Financial Calculations'!$C$25,G5<'Financial Calculations'!$I$25), "💙 STEADY", "⚠️ AVOID"))) -> ⚠️ AVOID | I5: =RANK(C5,$C$4:$C$23,0) -> 16
A6: ='Financial Calculations'!A7 -> HDFC Top 100 Fund | B6: ='Financial Calculations'!B7 -> Equity | C6: ='Financial Calculations'!E7 -> 0.13150727 | D6: ='Financial Calculations'!F7 -> 0.38096841 | E6: ='Financial Calculations'!G7 -> 0.00070726519 | F6: ='Financial Calculations'!H7 -> 1.05 | G6: ='Financial Calculations'!I7 -> 15.62 | H6: =IF(AND(C6>='Financial Calculations'!$C$25,G6<'Financial Calculations'!$I$25), "⭐ STAR", IF(AND(C6>='Financial Calculations'!$C$25,G6>='Financial Calculations'!$I$25), "🔥 AGGRESSIVE", IF(AND(C6<'Financial Calculations'!$C$25,G6<'Financial Calculations'!$I$25), "💙 STEADY", "⚠️ AVOID"))) -> ⚠️ AVOID | I6: =RANK(C6,$C$4:$C$23,0) -> 10
A7: ='Financial Calculations'!A8 -> Kotak Standard Multicap | B7: ='Financial Calculations'!B8 -> Equity | C7: ='Financial Calculations'!E8 -> 0.11914248 | D7: ='Financial Calculations'!F8 -> 0.31575673 | E7: ='Financial Calculations'!G8 -> -0.0099775204 | F7: ='Financial Calculations'!H8 -> 1.02 | G7: ='Financial Calculations'!I8 -> 14.93 | H7: =IF(AND(C7>='Financial Calculations'!$C$25,G7<'Financial Calculations'!$I$25), "⭐ STAR", IF(AND(C7>='Financial Calculations'!$C$25,G7>='Financial Calculations'!$I$25), "🔥 AGGRESSIVE", IF(AND(C7<'Financial Calculations'!$C$25,G7<'Financial Calculations'!$I$25), "💙 STEADY", "⚠️ AVOID"))) -> ⚠️ AVOID | I7: =RANK(C7,$C$4:$C$23,0) -> 13
A8: ='Financial Calculations'!A9 -> SBI Blue Chip Fund | B8: ='Financial Calculations'!B9 -> Equity | C8: ='Financial Calculations'!E9 -> 0.11036243 | D8: ='Financial Calculations'!F9 -> 0.27168862 | E8: ='Financial Calculations'!G9 -> -0.014837567 | F8: ='Financial Calculations'!H9 -> 0.95 | G8: ='Financial Calculations'!I9 -> 14.12 | H8: =IF(AND(C8>='Financial Calculations'!$C$25,G8<'Financial Calculations'!$I$25), "⭐ STAR", IF(AND(C8>='Financial Calculations'!$C$25,G8>='Financial Calculations'!$I$25), "🔥 AGGRESSIVE", IF(AND(C8<'Financial Calculations'!$C$25,G8<'Financial Calculations'!$I$25), "💙 STEADY", "⚠️ AVOID"))) -> ⚠️ AVOID | I8: =RANK(C8,$C$4:$C$23,0) -> 14
A9: ='Financial Calculations'!A10 -> Parag Parikh Flexi Cap | B9: ='Financial Calculations'!B10 -> Equity | C9: ='Financial Calculations'!E10 -> 0.14491611 | D9: ='Financial Calculations'!F10 -> 0.5393203 | E9: ='Financial Calculations'!G10 -> 0.023636105 | F9: ='Financial Calculations'!H10 -> 0.88 | G9: ='Financial Calculations'!I10 -> 13.52 | H9: =IF(AND(C9>='Financial Calculations'!$C$25,G9<'Financial Calculations'!$I$25), "⭐ STAR", IF(AND(C9>='Financial Calculations'!$C$25,G9>='Financial Calculations'!$I$25), "🔥 AGGRESSIVE", IF(AND(C9<'Financial Calculations'!$C$25,G9<'Financial Calculations'!$I$25), "💙 STEADY", "⚠️ AVOID"))) -> ⚠️ AVOID | I9: =RANK(C9,$C$4:$C$23,0) -> 7
A10: ='Financial Calculations'!A11 -> Nippon India Small Cap | B10: ='Financial Calculations'!B11 -> Equity | C10: ='Financial Calculations'!E11 -> 0.25994797 | D10: ='Financial Calculations'!F11 -> 0.94875298 | E10: ='Financial Calculations'!G11 -> 0.12186797 | F10: ='Financial Calculations'!H11 -> 1.18 | G10: ='Financial Calculations'!I11 -> 19.81 | H10: =IF(AND(C10>='Financial Calculations'!$C$25,G10<'Financial Calculations'!$I$25), "⭐ STAR", IF(AND(C10>='Financial Calculations'!$C$25,G10>='Financial Calculations'!$I$25), "🔥 AGGRESSIVE", IF(AND(C10<'Financial Calculations'!$C$25,G10<'Financial Calculations'!$I$25), "💙 STEADY", "⚠️ AVOID"))) -> ⚠️ AVOID | I10: =RANK(C10,$C$4:$C$23,0) -> 2
A11: ='Financial Calculations'!A12 -> HDFC Mid-Cap Opportunities | B11: ='Financial Calculations'!B12 -> Equity | C11: ='Financial Calculations'!E12 -> 0.19487207 | D11: ='Financial Calculations'!F12 -> 0.67401025 | E11: ='Financial Calculations'!G12 -> 0.060152069 | F11: ='Financial Calculations'!H12 -> 1.12 | G11: ='Financial Calculations'!I12 -> 18.23 | H11: =IF(AND(C11>='Financial Calculations'!$C$25,G11<'Financial Calculations'!$I$25), "⭐ STAR", IF(AND(C11>='Financial Calculations'!$C$25,G11>='Financial Calculations'!$I$25), "🔥 AGGRESSIVE", IF(AND(C11<'Financial Calculations'!$C$25,G11<'Financial Calculations'!$I$25), "💙 STEADY", "⚠️ AVOID"))) -> ⚠️ AVOID | I11: =RANK(C11,$C$4:$C$23,0) -> 3
A12: ='Financial Calculations'!A13 -> Aditya Birla PSU Equity | B12: ='Financial Calculations'!B13 -> Equity | C12: ='Financial Calculations'!E13 -> 0.26895931 | D12: ='Financial Calculations'!F13 -> 0.87889026 | E12: ='Financial Calculations'!G13 -> 0.12863931 | F12: ='Financial Calculations'!H13 -> 1.22 | G12: ='Financial Calculations'!I13 -> 22.41 | H12: =IF(AND(C12>='Financial Calculations'!$C$25,G12<'Financial Calculations'!$I$25), "⭐ STAR", IF(AND(C12>='Financial Calculations'!$C$25,G12>='Financial Calculations'!$I$25), "🔥 AGGRESSIVE", IF(AND(C12<'Financial Calculations'!$C$25,G12<'Financial Calculations'!$I$25), "💙 STEADY", "⚠️ AVOID"))) -> ⚠️ AVOID | I12: =RANK(C12,$C$4:$C$23,0) -> 1
A13: ='Financial Calculations'!A14 -> DSP Midcap Fund | B13: ='Financial Calculations'!B14 -> Equity | C13: ='Financial Calculations'!E14 -> 0.18389768 | D13: ='Financial Calculations'!F14 -> 0.63868538 | E13: ='Financial Calculations'!G14 -> 0.051417679 | F13: ='Financial Calculations'!H14 -> 1.08 | G13: ='Financial Calculations'!I14 -> 17.52 | H13: =IF(AND(C13>='Financial Calculations'!$C$25,G13<'Financial Calculations'!$I$25), "⭐ STAR", IF(AND(C13>='Financial Calculations'!$C$25,G13>='Financial Calculations'!$I$25), "🔥 AGGRESSIVE", IF(AND(C13<'Financial Calculations'!$C$25,G13<'Financial Calculations'!$I$25), "💙 STEADY", "⚠️ AVOID"))) -> ⚠️ AVOID | I13: =RANK(C13,$C$4:$C$23,0) -> 4
A14: ='Financial Calculations'!A15 -> SBI Magnum Gilt Fund | B14: ='Financial Calculations'!B15 -> Debt | C14: ='Financial Calculations'!E15 -> 0.070066111 | D14: ='Financial Calculations'!F15 -> -0.046044975 | E14: ='Financial Calculations'!G15 -> -0.012013889 | F14: ='Financial Calculations'!H15 -> 0.18 | G14: ='Financial Calculations'!I15 -> 4.2 | H14: =IF(AND(C14>='Financial Calculations'!$C$25,G14<'Financial Calculations'!$I$25), "⭐ STAR", IF(AND(C14>='Financial Calculations'!$C$25,G14>='Financial Calculations'!$I$25), "🔥 AGGRESSIVE", IF(AND(C14<'Financial Calculations'!$C$25,G14<'Financial Calculations'!$I$25), "💙 STEADY", "⚠️ AVOID"))) -> 💙 STEADY | I14: =RANK(C14,$C$4:$C$23,0) -> 19
A15: ='Financial Calculations'!A16 -> HDFC Corporate Bond Fund | B15: ='Financial Calculations'!B16 -> Debt | C15: ='Financial Calculations'!E16 -> 0.08985976 | D15: ='Financial Calculations'!F16 -> 0.46999368 | E15: ='Financial Calculations'!G16 -> 0.00553976 | F15: ='Financial Calculations'!H16 -> 0.22 | G15: ='Financial Calculations'!I16 -> 3.8 | H15: =IF(AND(C15>='Financial Calculations'!$C$25,G15<'Financial Calculations'!$I$25), "⭐ STAR", IF(AND(C15>='Financial Calculations'!$C$25,G15>='Financial Calculations'!$I$25), "🔥 AGGRESSIVE", IF(AND(C15<'Financial Calculations'!$C$25,G15<'Financial Calculations'!$I$25), "💙 STEADY", "⚠️ AVOID"))) -> 💙 STEADY | I15: =RANK(C15,$C$4:$C$23,0) -> 15
... A23: ='Financial Calculations'!A24 -> Canara Robeco Equity Hybrid | B23: ='Financial Calculations'!B24 -> Hybrid | C23: ='Financial Calculations'!E24 -> 0.12066044 | D23: ='Financial Calculations'!F24 -> 0.42313423 | E23: ='Financial Calculations'!G24 -> 0.0072204361 | F23: ='Financial Calculations'!H24 -> 0.74 | G23: ='Financial Calculations'!I24 -> 11.5 | H23: =IF(AND(C23>='Financial Calculations'!$C$25,G23<'Financial Calculations'!$I$25), "⭐ STAR", IF(AND(C23>='Financial Calculations'!$C$25,G23>='Financial Calculations'!$I$25), "🔥 AGGRESSIVE", IF(AND(C23<'Financial Calculations'!$C$25,G23<'Financial Calculations'!$I$25), "💙 STEADY", "⚠️ AVOID"))) -> 💙 STEADY | I23: =RANK(C23,$C$4:$C$23,0) -> 12

Sheet Expense Ratio Analysis
A3: Fund Name | B3: Category | C3: Expense Ratio % | D3: 5Y CAGR | E3: Net Return (5Y − Expense) | F3: Sharpe Ratio | G3: Cost Efficiency Grade | H3: Cost Rank
A4: ='Financial Calculations'!A5 -> Mirae Asset Large Cap Fund | B4: ='Financial Calculations'!B5 -> Equity | C4: ='Financial Calculations'!J5 -> 0.0054 | D4: ='Financial Calculations'!E5 -> 0.16232457 | E4: =D4-C4 -> 0.15692457 | F4: ='Financial Calculations'!F5 -> 0.6360885 | G4: =IF(AND(C4<0.007,D4>0.15),"A+ Excellent", IF(AND(C4<0.009,D4>0.12),"A Good", IF(C4<0.012,"B Average", "C Expensive"))) -> A+ Excellent | H4: =RANK(C4,$C$4:$C$23,1) -> 8
A5: ='Financial Calculations'!A6 -> Axis Bluechip Fund | B5: ='Financial Calculations'!B6 -> Equity | C5: ='Financial Calculations'!J6 -> 0.0058 | D5: ='Financial Calculations'!E6 -> 0.08304551 | E5: =D5-C5 -> 0.07724551 | F5: ='Financial Calculations'!F6 -> 0.079866307 | G5: =IF(AND(C5<0.007,D5>0.15),"A+ Excellent", IF(AND(C5<0.009,D5>0.12),"A Good", IF(C5<0.012,"B Average", "C Expensive"))) -> B Average | H5: =RANK(C5,$C$4:$C$23,1) -> 9
A6: ='Financial Calculations'!A7 -> HDFC Top 100 Fund | B6: ='Financial Calculations'!B7 -> Equity | C6: ='Financial Calculations'!J7 -> 0.0165 | D6: ='Financial Calculations'!E7 -> 0.13150727 | E6: =D6-C6 -> 0.11500727 | F6: ='Financial Calculations'!F7 -> 0.38096841 | G6: =IF(AND(C6<0.007,D6>0.15),"A+ Excellent", IF(AND(C6<0.009,D6>0.12),"A Good", IF(C6<0.012,"B Average", "C Expensive"))) -> C Expensive | H6: =RANK(C6,$C$4:$C$23,1) -> 19
A7: ='Financial Calculations'!A8 -> Kotak Standard Multicap | B7: ='Financial Calculations'!B8 -> Equity | C7: ='Financial Calculations'!J8 -> 0.0058 | D7: ='Financial Calculations'!E8 -> 0.11914248 | E7: =D7-C7 -> 0.11334248 | F7: ='Financial Calculations'!F8 -> 0.31575673 | G7: =IF(AND(C7<0.007,D7>0.15),"A+ Excellent", IF(AND(C7<0.009,D7>0.12),"A Good", IF(C7<0.012,"B Average", "C Expensive"))) -> B Average | H7: =RANK(C7,$C$4:$C$23,1) -> 9
A8: ='Financial Calculations'!A9 -> SBI Blue Chip Fund | B8: ='Financial Calculations'!B9 -> Equity | C8: ='Financial Calculations'!J9 -> 0.0098 | D8: ='Financial Calculations'!E9 -> 0.11036243 | E8: =D8-C8 -> 0.10056243 | F8: ='Financial Calculations'!F9 -> 0.27168862 | G8: =IF(AND(C8<0.007,D8>0.15),"A+ Excellent", IF(AND(C8<0.009,D8>0.12),"A Good", IF(C8<0.012,"B Average", "C Expensive"))) -> B Average | H8: =RANK(C8,$C$4:$C$23,1) -> 17
A9: ='Financial Calculations'!A10 -> Parag Parikh Flexi Cap | B9: ='Financial Calculations'!B10 -> Equity | C9: ='Financial Calculations'!J10 -> 0.0063 | D9: ='Financial Calculations'!E10 -> 0.14491611 | E9: =D9-C9 -> 0.13861611 | F9: ='Financial Calculations'!F10 -> 0.5393203 | G9: =IF(AND(C9<0.007,D9>0.15),"A+ Excellent", IF(AND(C9<0.009,D9>0.12),"A Good", IF(C9<0.012,"B Average", "C Expensive"))) -> A Good | H9: =RANK(C9,$C$4:$C$23,1) -> 12
A10: ='Financial Calculations'!A11 -> Nippon India Small Cap | B10: ='Financial Calculations'!B11 -> Equity | C10: ='Financial Calculations'!J11 -> 0.0074 | D10: ='Financial Calculations'!E11 -> 0.25994797 | E10: =D10-C10 -> 0.25254797 | F10: ='Financial Calculations'!F11 -> 0.94875298 | G10: =IF(AND(C10<0.007,D10>0.15),"A+ Excellent", IF(AND(C10<0.009,D10>0.12),"A Good", IF(C10<0.012,"B Average", "C Expensive"))) -> A Good | H10: =RANK(C10,$C$4:$C$23,1) -> 14
A11: ='Financial Calculations'!A12 -> HDFC Mid-Cap Opportunities | B11: ='Financial Calculations'!B12 -> Equity | C11: ='Financial Calculations'!J12 -> 0.0165 | D11: ='Financial Calculations'!E12 -> 0.19487207 | E11: =D11-C11 -> 0.17837207 | F11: ='Financial Calculations'!F12 -> 0.67401025 | G11: =IF(AND(C11<0.007,D11>0.15),"A+ Excellent", IF(AND(C11<0.009,D11>0.12),"A Good", IF(C11<0.012,"B Average", "C Expensive"))) -> C Expensive | H11: =RANK(C11,$C$4:$C$23,1) -> 19
A12: ='Financial Calculations'!A13 -> Aditya Birla PSU Equity | B12: ='Financial Calculations'!B13 -> Equity | C12: ='Financial Calculations'!J13 -> 0.0051 | D12: ='Financial Calculations'!E13 -> 0.26895931 | E12: =D12-C12 -> 0.26385931 | F12: ='Financial Calculations'!F13 -> 0.87889026 | G12: =IF(AND(C12<0.007,D12>0.15),"A+ Excellent", IF(AND(C12<0.009,D12>0.12),"A Good", IF(C12<0.012,"B Average", "C Expensive"))) -> A+ Excellent | H12: =RANK(C12,$C$4:$C$23,1) -> 7
A13: ='Financial Calculations'!A14 -> DSP Midcap Fund | B13: ='Financial Calculations'!B14 -> Equity | C13: ='Financial Calculations'!J14 -> 0.0085 | D13: ='Financial Calculations'!E14 -> 0.18389768 | E13: =D13-C13 -> 0.17539768 | F13: ='Financial Calculations'!F14 -> 0.63868538 | G13: =IF(AND(C13<0.007,D13>0.15),"A+ Excellent", IF(AND(C13<0.009,D13>0.12),"A Good", IF(C13<0.012,"B Average", "C Expensive"))) -> A Good | H13: =RANK(C13,$C$4:$C$23,1) -> 16
A14: ='Financial Calculations'!A15 -> SBI Magnum Gilt Fund | B14: ='Financial Calculations'!B15 -> Debt | C14: ='Financial Calculations'!J15 -> 0.0046 | D14: ='Financial Calculations'!E15 -> 0.070066111 | E14: =D14-C14 -> 0.065466111 | F14: ='Financial Calculations'!F15 -> -0.046044975 | G14: =IF(AND(C14<0.007,D14>0.15),"A+ Excellent", IF(AND(C14<0.009,D14>0.12),"A Good", IF(C14<0.012,"B Average", "C Expensive"))) -> B Average | H14: =RANK(C14,$C$4:$C$23,1) -> 5
A15: ='Financial Calculations'!A16 -> HDFC Corporate Bond Fund | B15: ='Financial Calculations'!B16 -> Debt | C15: ='Financial Calculations'!J16 -> 0.0038 | D15: ='Financial Calculations'!E16 -> 0.08985976 | E15: =D15-C15 -> 0.08605976 | F15: ='Financial Calculations'!F16 -> 0.46999368 | G15: =IF(AND(C15<0.007,D15>0.15),"A+ Excellent", IF(AND(C15<0.009,D15>0.12),"A Good", IF(C15<0.012,"B Average", "C Expensive"))) -> B Average | H15: =RANK(C15,$C$4:$C$23,1) -> 2
... A23: ='Financial Calculations'!A24 -> Canara Robeco Equity Hybrid | B23: ='Financial Calculations'!B24 -> Hybrid | C23: ='Financial Calculations'!J24 -> 0.0066 | D23: ='Financial Calculations'!E24 -> 0.12066044 | E23: =D23-C23 -> 0.11406044 | F23: ='Financial Calculations'!F24 -> 0.42313423 | G23: =IF(AND(C23<0.007,D23>0.15),"A+ Excellent", IF(AND(C23<0.009,D23>0.12),"A Good", IF(C23<0.012,"B Average", "C Expensive"))) -> A Good | H23: =RANK(C23,$C$4:$C$23,1) -> 13
A26: Average Expense Ratio by Category:
A27: Equity avg return: | B27: =AVERAGEIF($B$4:$B$23,"Equity",$D$4:$D$23) -> 0.16589754
A28: Debt avg return: | B28: =AVERAGEIF($B$4:$B$23,"Debt",$D$4:$D$23) -> 0.075415775
A29: Hybrid avg return: | B29: =AVERAGEIF($B$4:$B$23,"Hybrid",$D$4:$D$23) -> 0.13547083

Sheet NAV Trend Data
A1: Fund | B1: Q1 2020 | C1: Q2 2020 | D1: Q3 2020 | E1: Q4 2020 | F1: Q1 2021 | G1: Q2 2021 | H1: Q3 2021 | I1: Q4 2021 | J1: Q1 2022 | K1: Q2 2022 | L1: Q3 2022 | M1: Q4 2022 | N1: Q1 2023 | O1: Q2 2023 | P1: Q3 2023 | Q1: Q4 2023 | R1: Q1 2024 | S1: Q2 2024 | T1: Q3 2024 | U1: Q4 2024 | V1: Q1 2025
A2: Parag Parikh Flexi Cap | B2: 26.4 | C2: 19 | D2: 23.2 | E2: 25.9 | F2: 28 | G2: 30.6 | H2: 33.1 | I2: 36.4 | J2: 33.5 | K2: 31.4 | L2: 33.2 | M2: 35.2 | N2: 37.7 | O2: 40.4 | P2: 43.5 | Q2: 47 | R2: 49.6 | S2: 54.1 | T2: 57.4 | U2: 60.2 | V2: 84.2
A3: Nippon India Small Cap | B3: 18.6 | C3: 13.4 | D3: 16.4 | E3: 18.2 | F3: 19.6 | G3: 21.5 | H3: 23.2 | I3: 25.6 | J3: 23.5 | K3: 22 | L3: 23.3 | M3: 24.6 | N3: 26.4 | O3: 28.2 | P3: 30.5 | Q3: 33 | R3: 34.7 | S3: 37.9 | T3: 40.2 | U3: 42.2 | V3: 112.4
A4: HDFC Hybrid Equity | B4: 42.6 | C4: 30.7 | D4: 37.5 | E4: 41.7 | F4: 44.9 | G4: 49.1 | H4: 53.1 | I4: 58.5 | J4: 53.7 | K4: 50.4 | L4: 53.3 | M4: 56.4 | N4: 60.4 | O4: 64.7 | P4: 69.8 | Q4: 75.4 | R4: 79.5 | S4: 86.7 | T4: 92 | U4: 96.5 | V4: 80.4
A5: SBI Magnum Gilt Fund | B5: 40.2 | C5: 42.1 | D5: 43.5 | E5: 44.2 | F5: 44.9 | G5: 45.4 | H5: 46.1 | I5: 46.8 | J5: 47.3 | K5: 47.6 | L5: 48.2 | M5: 48.8 | N5: 49.4 | O5: 50.1 | P5: 50.8 | Q5: 51.6 | R5: 52.3 | S5: 53.4 | T5: 54.1 | U5: 55.2 | V5: 56.4
A6: HDFC Corporate Bond Fund | B6: 18.6 | C6: 19.2 | D6: 19.8 | E6: 20.2 | F6: 20.6 | G6: 21 | H6: 21.4 | I6: 21.9 | J6: 22.2 | K6: 22.4 | L6: 22.7 | M6: 23 | N6: 23.4 | O6: 23.8 | P6: 24.2 | Q6: 24.7 | R6: 25.1 | S6: 25.8 | T6: 26.3 | U6: 27.1 | V6: 28.6
